[{"rating":90,"name":"Greek Chicken Pasta","link":"/Recipe/Greek-Chicken-Pasta/Detail.aspx?evt19=1&referringHubId=84","type":"healthy"},{"rating":90,"name":"Grandma's Chicken Noodle Soup","link":"/Recipe/Grandmas-Chicken-Noodle-Soup/Detail.aspx?evt19=1&referringHubId=84","type":"healthy"},{"rating":90,"name":"Penne with Chicken and Asparagus","link":"/Recipe/Penne-with-Chicken-and-Asparagus/Detail.aspx?evt19=1&referringHubId=84","type":"healthy"},{"rating":90,"name":"Basil Chicken over Angel Hair","link":"/Recipe/Basil-Chicken-over-Angel-Hair/Detail.aspx?evt19=1&referringHubId=84","type":"healthy"},{"rating":90,"name":"Roasted Garlic Lemon Broccoli","link":"/Recipe/Roasted-Garlic-Lemon-Broccoli/Detail.aspx?evt19=1&referringHubId=84","type":"healthy"},{"rating":80,"name":"Healthy Banana Cookies","link":"/Recipe/Healthy-Banana-Cookies/Detail.aspx?evt19=1&referringHubId=84","type":"healthy"},{"rating":90,"name":"Laura's Quick Slow Cooker Turkey Chili","link":"/Recipe/Lauras-Quick-Slow-Cooker-Turkey-Chili/Detail.aspx?evt19=1&referringHubId=84","type":"healthy"},{"rating":90,"name":"Vegetarian Chickpea Sandwich Filling","link":"/Recipe/Vegetarian-Chickpea-Sandwich-Filling/Detail.aspx?evt19=1&referringHubId=84","type":"healthy"},{"rating":90,"name":"White Bean Chicken Chili","link":"/Recipe/White-Bean-Chicken-Chili/Detail.aspx?evt19=1&referringHubId=84","type":"healthy"},{"rating":90,"name":"D's Famous Salsa","link":"/Recipe/Ds-Famous-Salsa/Detail.aspx?evt19=1&referringHubId=84","type":"healthy"},{"rating":90,"name":"Easy Baked Tilapia","link":"/Recipe/Easy-Baked-Tilapia/Detail.aspx?evt19=1&referringHubId=84","type":"healthy"},{"rating":90,"name":"Black Beans and Rice","link":"/Recipe/Black-Beans-and-Rice/Detail.aspx?evt19=1&referringHubId=84","type":"healthy"},{"rating":90,"name":"Low-Fat Blueberry Bran Muffins","link":"/Recipe/Low-Fat-Blueberry-Bran-Muffins/Detail.aspx?evt19=1&referringHubId=84","type":"healthy"},{"rating":90,"name":"Penne Pasta with Spinach and Bacon","link":"/Recipe/Penne-Pasta-with-Spinach-and-Bacon/Detail.aspx?evt19=1&referringHubId=84","type":"healthy"},{"rating":100,"name":"Morning Glory Muffins I","link":"/Recipe/Morning-Glory-Muffins-I/Detail.aspx?evt19=1&referringHubId=84","type":"healthy"},{"rating":90,"name":"Split Pea Soup","link":"/Recipe/Split-Pea-Soup/Detail.aspx?evt19=1&referringHubId=84","type":"healthy"},{"rating":90,"name":"Fantastic Black Bean Chili","link":"/Recipe/Fantastic-Black-Bean-Chili/Detail.aspx?evt19=1&referringHubId=84","type":"healthy"},{"rating":90,"name":"Easy Pizza Sauce III","link":"/Recipe/Easy-Pizza-Sauce-III/Detail.aspx?evt19=1&referringHubId=84","type":"healthy"},{"rating":90,"name":"Grilled Fish Tacos with Chipotle-Lime Dressing","link":"/Recipe/Grilled-Fish-Tacos-with-Chipotle-Lime-Dressing/Detail.aspx?evt19=1&referringHubId=84","type":"healthy"},{"rating":90,"name":"Strawberry Oatmeal Breakfast Smoothie","link":"/Recipe/Strawberry-Oatmeal-Breakfast-Smoothie/Detail.aspx?evt19=1&referringHubId=84","type":"healthy"},{"rating":90,"name":"Whole Wheat Honey Bread","link":"/Recipe/Whole-Wheat-Honey-Bread/Detail.aspx?evt19=1&referringHubId=84","type":"healthy"},{"rating":90,"name":"Salsa Chicken Burrito Filling","link":"/Recipe/Salsa-Chicken-Burrito-Filling/Detail.aspx?evt19=1&referringHubId=84","type":"healthy"},{"rating":90,"name":"Emily's Famous Hash Browns","link":"/Recipe/Emilys-Famous-Hash-Browns/Detail.aspx?evt19=1&referringHubId=84","type":"healthy"},{"rating":90,"name":"Bean Soup With Kale","link":"/Recipe/Bean-Soup-With-Kale/Detail.aspx?evt19=1&referringHubId=84","type":"healthy"},{"rating":90,"name":"Health Nut Blueberry Muffins","link":"/Recipe/Health-Nut-Blueberry-Muffins/Detail.aspx?evt19=1&referringHubId=84","type":"healthy"},{"rating":80,"name":"Chicken and Red Wine Sauce","link":"/Recipe/Chicken-and-Red-Wine-Sauce/Detail.aspx?evt19=1&referringHubId=84","type":"healthy"},{"rating":90,"name":"Pesto Pasta with Chicken","link":"/Recipe/Pesto-Pasta-with-Chicken/Detail.aspx?evt19=1&referringHubId=84","type":"healthy"},{"rating":90,"name":"Grandma's Slow Cooker Vegetarian Chili","link":"/Recipe/Grandmas-Slow-Cooker-Vegetarian-Chili/Detail.aspx?evt19=1&referringHubId=84","type":"healthy"},{"rating":100,"name":"Spinach and Feta Pita Bake","link":"/Recipe/Spinach-and-Feta-Pita-Bake/Detail.aspx?evt19=1&referringHubId=84","type":"healthy"},{"rating":90,"name":"Fiery Fish Tacos with Crunchy Corn Salsa","link":"/Recipe/Fiery-Fish-Tacos-with-Crunchy-Corn-Salsa/Detail.aspx?evt19=1&referringHubId=84","type":"healthy"},{"rating":90,"name":"Pineapple Chicken Tenders","link":"/Recipe/Pineapple-Chicken-Tenders/Detail.aspx?evt19=1&referringHubId=84","type":"healthy"},{"rating":90,"name":"Andrea's Pasta Fagioli","link":"/Recipe/Andreas-Pasta-Fagioli/Detail.aspx?evt19=1&referringHubId=84","type":"healthy"},{"rating":90,"name":"Chicken and Corn Chili","link":"/Recipe/Chicken-and-Corn-Chili/Detail.aspx?evt19=1&referringHubId=84","type":"healthy"},{"rating":90,"name":"Fajita Marinade I","link":"/Recipe/Fajita-Marinade-I/Detail.aspx?evt19=1&referringHubId=84","type":"healthy"},{"rating":90,"name":"Fresh Tomato Salsa","link":"/Recipe/Fresh-Tomato-Salsa/Detail.aspx?evt19=1&referringHubId=84","type":"healthy"},{"rating":90,"name":"Zucchini and Potato Bake","link":"/Recipe/Zucchini-and-Potato-Bake/Detail.aspx?evt19=1&referringHubId=84","type":"healthy"},{"rating":90,"name":"Hawaiian Chicken Kabobs","link":"/Recipe/Hawaiian-Chicken-Kabobs/Detail.aspx?evt19=1&referringHubId=84","type":"healthy"},{"rating":90,"name":"Balsamic Bruschetta","link":"/Recipe/Balsamic-Bruschetta/Detail.aspx?evt19=1&referringHubId=84","type":"healthy"},{"rating":100,"name":"Out of this World Turkey Brine","link":"/Recipe/Out-of-this-World-Turkey-Brine/Detail.aspx?evt19=1&referringHubId=84","type":"healthy"},{"rating":90,"name":"Whole Wheat Blueberry Pancakes","link":"/Recipe/Whole-Wheat-Blueberry-Pancakes/Detail.aspx?evt19=1&referringHubId=84","type":"healthy"},{"rating":90,"name":"Fra Diavolo Sauce With Pasta","link":"/Recipe/Fra-Diavolo-Sauce-With-Pasta/Detail.aspx?evt19=1&referringHubId=84","type":"healthy"},{"rating":90,"name":"Mock Tuna Salad","link":"/Recipe/Mock-Tuna-Salad/Detail.aspx?evt19=1&referringHubId=84","type":"healthy"},{"rating":90,"name":"Best Black Beans","link":"/Recipe/Best-Black-Beans/Detail.aspx?evt19=1&referringHubId=84","type":"healthy"},{"rating":90,"name":"Spiced Sweet Roasted Red Pepper Hummus","link":"/Recipe/Spiced-Sweet-Roasted-Red-Pepper-Hummus/Detail.aspx?evt19=1&referringHubId=84","type":"healthy"},{"rating":90,"name":"Whole Wheat Beer Bread","link":"/Recipe/Whole-Wheat-Beer-Bread/Detail.aspx?evt19=1&referringHubId=84","type":"healthy"},{"rating":90,"name":"Sesame Green Beans","link":"/Recipe/Sesame-Green-Beans/Detail.aspx?evt19=1&referringHubId=84","type":"healthy"},{"rating":80,"name":"Chicken Satay","link":"/Recipe/Chicken-Satay/Detail.aspx?evt19=1&referringHubId=84","type":"healthy"},{"rating":90,"name":"Quinoa Side Dish","link":"/Recipe/Quinoa-Side-Dish/Detail.aspx?evt19=1&referringHubId=84","type":"healthy"},{"rating":90,"name":"Easy Apple Coleslaw","link":"/Recipe/Easy-Apple-Coleslaw/Detail.aspx?evt19=1&referringHubId=84","type":"healthy"},{"rating":80,"name":"Chickpea Curry","link":"/Recipe/Chickpea-Curry/Detail.aspx?evt19=1&referringHubId=84","type":"healthy"},{"rating":90,"name":"Extra Easy Hummus","link":"/Recipe/Extra-Easy-Hummus/Detail.aspx?evt19=1&referringHubId=84","type":"healthy"},{"rating":80,"name":"Garlic Chicken with Orzo Noodles","link":"/Recipe/Garlic-Chicken-with-Orzo-Noodles/Detail.aspx?evt19=1&referringHubId=84","type":"healthy"},{"rating":80,"name":"Spicy Baked Sweet Potato Fries","link":"/Recipe/Spicy-Baked-Sweet-Potato-Fries/Detail.aspx?evt19=1&referringHubId=84","type":"healthy"},{"rating":90,"name":"Garlic Shrimp Linguine","link":"/Recipe/Garlic-Shrimp-Linguine/Detail.aspx?evt19=1&referringHubId=84","type":"healthy"},{"rating":90,"name":"Whole Wheat and Honey Pizza Dough","link":"/Recipe/Whole-Wheat-and-Honey-Pizza-Dough/Detail.aspx?evt19=1&referringHubId=84","type":"healthy"},{"rating":90,"name":"Simple Baked Apples","link":"/Recipe/Simple-Baked-Apples/Detail.aspx?evt19=1&referringHubId=84","type":"healthy"},{"rating":80,"name":"Turkey Veggie Meatloaf Cups","link":"/Recipe/Turkey-Veggie-Meatloaf-Cups/Detail.aspx?evt19=1&referringHubId=84","type":"healthy"},{"rating":90,"name":"Baked Sweet Potatoes","link":"/Recipe/Baked-Sweet-Potatoes/Detail.aspx?evt19=1&referringHubId=84","type":"healthy"},{"rating":90,"name":"Spicy Chicken Breasts","link":"/Recipe/Spicy-Chicken-Breasts/Detail.aspx?evt19=1&referringHubId=84","type":"healthy"},{"rating":80,"name":"Cod with Italian Crumb Topping","link":"/Recipe/Cod-with-Italian-Crumb-Topping/Detail.aspx?evt19=1&referringHubId=84","type":"healthy"},{"rating":90,"name":"Spinach and Sun-Dried Tomato Pasta","link":"/Recipe/Spinach-and-Sun-Dried-Tomato-Pasta/Detail.aspx?evt19=1&referringHubId=84","type":"healthy"},{"rating":80,"name":"Bourbon Chicken","link":"/Recipe/Bourbon-Chicken/Detail.aspx?evt19=1&referringHubId=84","type":"healthy"},{"rating":90,"name":"White Chili I","link":"/Recipe/White-Chili-I/Detail.aspx?evt19=1&referringHubId=84","type":"healthy"},{"rating":80,"name":"Greek Pasta with Tomatoes and White Beans","link":"/Recipe/Greek-Pasta-with-Tomatoes-and-White-Beans/Detail.aspx?evt19=1&referringHubId=84","type":"healthy"},{"rating":90,"name":"Moroccan Lentil Soup","link":"/Recipe/Moroccan-Lentil-Soup/Detail.aspx?evt19=1&referringHubId=84","type":"healthy"},{"rating":100,"name":"Flax and Sunflower Seed Bread","link":"/Recipe/Flax-and-Sunflower-Seed-Bread/Detail.aspx?evt19=1&referringHubId=84","type":"healthy"},{"rating":90,"name":"Mimi's Giant Whole-Wheat Banana-Strawberry Muffins","link":"/Recipe/Mimis-Giant-Whole-Wheat-Banana-Strawberry-Muffins/Detail.aspx?evt19=1&referringHubId=84","type":"healthy"},{"rating":90,"name":"Black-Eyed Pea Gumbo","link":"/Recipe/Black-Eyed-Pea-Gumbo/Detail.aspx?evt19=1&referringHubId=84","type":"healthy"},{"rating":90,"name":"Insanely Easy Vegetarian Chili","link":"/Recipe/Insanely-Easy-Vegetarian-Chili/Detail.aspx?evt19=1&referringHubId=84","type":"healthy"},{"rating":90,"name":"Maple-Garlic Marinated Pork Tenderloin","link":"/Recipe/Maple-Garlic-Marinated-Pork-Tenderloin/Detail.aspx?evt19=1&referringHubId=84","type":"healthy"},{"rating":90,"name":"Spicy Slow Cooker Black Bean Soup","link":"/Recipe/Spicy-Slow-Cooker-Black-Bean-Soup/Detail.aspx?evt19=1&referringHubId=84","type":"healthy"},{"rating":90,"name":"Slow Cooker Spicy Black-Eyed Peas","link":"/Recipe/Slow-Cooker-Spicy-Black-Eyed-Peas/Detail.aspx?evt19=1&referringHubId=84","type":"healthy"},{"rating":90,"name":"Jenny's Grilled Chicken Breasts","link":"/Recipe/Jennys-Grilled-Chicken-Breasts/Detail.aspx?evt19=1&referringHubId=84","type":"healthy"},{"rating":80,"name":"Thai Peanut Chicken","link":"/Recipe/Thai-Peanut-Chicken/Detail.aspx?evt19=1&referringHubId=84","type":"healthy"},{"rating":80,"name":"T's Sweet Potato Fries","link":"/Recipe/Ts-Sweet-Potato-Fries/Detail.aspx?evt19=1&referringHubId=84","type":"healthy"},{"rating":90,"name":"Split Pea and Ham Soup I","link":"/Recipe/Split-Pea-and-Ham-Soup-I/Detail.aspx?evt19=1&referringHubId=84","type":"healthy"},{"rating":90,"name":"Baked Sweet Potato Sticks","link":"/Recipe/Baked-Sweet-Potato-Sticks-2/Detail.aspx?evt19=1&referringHubId=84","type":"healthy"},{"rating":90,"name":"Honey Whole Wheat Bread","link":"/Recipe/Honey-Whole-Wheat-Bread/Detail.aspx?evt19=1&referringHubId=84","type":"healthy"},{"rating":90,"name":"Pasta Fagioli","link":"/Recipe/Pasta-Fagioli/Detail.aspx?evt19=1&referringHubId=84","type":"healthy"},{"rating":90,"name":"Easy Grilled Chicken Teriyaki","link":"/Recipe/Easy-Grilled-Chicken-Teriyaki/Detail.aspx?evt19=1&referringHubId=84","type":"healthy"},{"rating":100,"name":"Super Al's Cocktail Sauce","link":"/Recipe/Super-Als-Cocktail-Sauce/Detail.aspx?evt19=1&referringHubId=84","type":"healthy"},{"rating":90,"name":"Baked Halibut Steaks","link":"/Recipe/Baked-Halibut-Steaks/Detail.aspx?evt19=1&referringHubId=84","type":"healthy"},{"rating":90,"name":"Kabob Marinade","link":"/Recipe/Kabob-Marinade/Detail.aspx?evt19=1&referringHubId=84","type":"healthy"},{"rating":90,"name":"Arrabbiata Sauce","link":"/Recipe/Arrabbiata-Sauce/Detail.aspx?evt19=1&referringHubId=84","type":"healthy"},{"rating":90,"name":"Jo-Ann's Power Bars","link":"/Recipe/Jo-Anns-Power-Bars/Detail.aspx?evt19=1&referringHubId=84","type":"healthy"},{"rating":90,"name":"A Jerky Chicken","link":"/Recipe/A-Jerky-Chicken/Detail.aspx?evt19=1&referringHubId=84","type":"healthy"},{"rating":80,"name":"Balsamic Glazed Carrots","link":"/Recipe/Balsamic-Glazed-Carrots/Detail.aspx?evt19=1&referringHubId=84","type":"healthy"},{"rating":90,"name":"Japanese-Style Sesame Green Beans","link":"/Recipe/Japanese-Style-Sesame-Green-Beans/Detail.aspx?evt19=1&referringHubId=84","type":"healthy"},{"rating":80,"name":"Asian Tuna Patties","link":"/Recipe/Asian-Tuna-Patties/Detail.aspx?evt19=1&referringHubId=84","type":"healthy"},{"rating":80,"name":"Slow Cooker Honey Garlic Chicken","link":"/Recipe/Slow-Cooker-Honey-Garlic-Chicken/Detail.aspx?evt19=1&referringHubId=84","type":"healthy"},{"rating":90,"name":"Baked Tortilla Chips","link":"/Recipe/Baked-Tortilla-Chips/Detail.aspx?evt19=1&referringHubId=84","type":"healthy"},{"rating":90,"name":"Microwave Corn on the Cob","link":"/Recipe/Microwave-Corn-on-the-Cob/Detail.aspx?evt19=1&referringHubId=84","type":"healthy"},{"rating":90,"name":"Cajun Style Baked Sweet Potato","link":"/Recipe/Cajun-Style-Baked-Sweet-Potato/Detail.aspx?evt19=1&referringHubId=84","type":"healthy"},{"rating":90,"name":"Bar-B-Que Sauce","link":"/Recipe/Bar-B-Que-Sauce/Detail.aspx?evt19=1&referringHubId=84","type":"healthy"},{"rating":90,"name":"Pico De Gallo","link":"/Recipe/Pico-De-Gallo/Detail.aspx?evt19=1&referringHubId=84","type":"healthy"},{"rating":90,"name":"Vegan Split Pea Soup I","link":"/Recipe/Vegan-Split-Pea-Soup-I/Detail.aspx?evt19=1&referringHubId=84","type":"healthy"},{"rating":90,"name":"Baked French Fries II","link":"/Recipe/Baked-French-Fries-II/Detail.aspx?evt19=1&referringHubId=84","type":"healthy"},{"rating":80,"name":"Grilled Peanut Chicken","link":"/Recipe/Grilled-Peanut-Chicken/Detail.aspx?evt19=1&referringHubId=84","type":"healthy"},{"rating":90,"name":"Microwave Popcorn","link":"/Recipe/Microwave-Popcorn/Detail.aspx?evt19=1&referringHubId=84","type":"healthy"},{"rating":90,"name":"Terry's Texas Pinto Beans","link":"/Recipe/Terrys-Texas-Pinto-Beans/Detail.aspx?evt19=1&referringHubId=84","type":"healthy"},{"rating":80,"name":"Rosemary Turkey Meatloaf","link":"/Recipe/Rosemary-Turkey-Meatloaf/Detail.aspx?evt19=1&referringHubId=84","type":"healthy"},{"rating":90,"name":"Easy White Chili","link":"/Recipe/Easy-White-Chili/Detail.aspx?evt19=1&referringHubId=84","type":"healthy"},{"rating":90,"name":"Sunday Best Fruit Salad","link":"/Recipe/Sunday-Best-Fruit-Salad/Detail.aspx?evt19=1&referringHubId=84","type":"healthy"},{"rating":80,"name":"Ranch Crispy Chicken","link":"/Recipe/Ranch-Crispy-Chicken/Detail.aspx?evt19=1&referringHubId=84","type":"healthy"},{"rating":90,"name":"Gnocchi I","link":"/Recipe/Gnocchi-I/Detail.aspx?evt19=1&referringHubId=84","type":"healthy"},{"rating":90,"name":"Quinoa with Chickpeas and Tomatoes","link":"/Recipe/Quinoa-with-Chickpeas-and-Tomatoes/Detail.aspx?evt19=1&referringHubId=84","type":"healthy"},{"rating":100,"name":"Creole Seasoning Blend","link":"/Recipe/Creole-Seasoning-Blend/Detail.aspx?evt19=1&referringHubId=84","type":"healthy"},{"rating":90,"name":"Tangy Grilled Pork Tenderloin","link":"/Recipe/Tangy-Grilled-Pork-Tenderloin/Detail.aspx?evt19=1&referringHubId=84","type":"healthy"},{"rating":90,"name":"Steakhouse Wheat Bread for the Bread Machine","link":"/Recipe/Steakhouse-Wheat-Bread-for-the-Bread-Machine/Detail.aspx?evt19=1&referringHubId=84","type":"healthy"},{"rating":90,"name":"Chicken in a Pot","link":"/Recipe/Chicken-in-a-Pot/Detail.aspx?evt19=1&referringHubId=84","type":"healthy"},{"rating":90,"name":"Greek Lentil Soup (Fakes)","link":"/Recipe/Greek-Lentil-Soup-Fakes/Detail.aspx?evt19=1&referringHubId=84","type":"healthy"},{"rating":90,"name":"Lower Fat Banana Bread II","link":"/Recipe/Lower-Fat-Banana-Bread-II/Detail.aspx?evt19=1&referringHubId=84","type":"healthy"},{"rating":90,"name":"Cranberry and Cilantro Quinoa Salad","link":"/Recipe/Cranberry-and-Cilantro-Quinoa-Salad/Detail.aspx?evt19=1&referringHubId=84","type":"healthy"},{"rating":90,"name":"Cajun Pasta Fresca","link":"/Recipe/Cajun-Pasta-Fresca/Detail.aspx?evt19=1&referringHubId=84","type":"healthy"},{"rating":90,"name":"RamJam Chicken","link":"/Recipe/RamJam-Chicken/Detail.aspx?evt19=1&referringHubId=84","type":"healthy"},{"rating":90,"name":"Simple Roasted Butternut Squash","link":"/Recipe/Simple-Roasted-Butternut-Squash/Detail.aspx?evt19=1&referringHubId=84","type":"healthy"},{"rating":80,"name":"Baked Chicken with Peaches","link":"/Recipe/Baked-Chicken-with-Peaches/Detail.aspx?evt19=1&referringHubId=84","type":"healthy"},{"rating":90,"name":"Vegan Bean Taco Filling","link":"/Recipe/Vegan-Bean-Taco-Filling/Detail.aspx?evt19=1&referringHubId=84","type":"healthy"},{"rating":90,"name":"Lentils And Spinach","link":"/Recipe/Lentils-And-Spinach/Detail.aspx?evt19=1&referringHubId=84","type":"healthy"},{"rating":90,"name":"Seminary Muffins","link":"/Recipe/Seminary-Muffins/Detail.aspx?evt19=1&referringHubId=84","type":"healthy"},{"rating":90,"name":"Groovy Green Smoothie","link":"/Recipe/Groovy-Green-Smoothie/Detail.aspx?evt19=1&referringHubId=84","type":"healthy"},{"rating":90,"name":"Miso Soup","link":"/Recipe/Miso-Soup/Detail.aspx?evt19=1&referringHubId=84","type":"healthy"},{"rating":90,"name":"Blue Cranberry Sauce","link":"/Recipe/Blue-Cranberry-Sauce/Detail.aspx?evt19=1&referringHubId=84","type":"healthy"},{"rating":90,"name":"Superfast Asparagus","link":"/Recipe/Superfast-Asparagus/Detail.aspx?evt19=1&referringHubId=84","type":"healthy"},{"rating":90,"name":"Espinacas con Garbanzos (Spinach with Garbanzo Beans)","link":"/Recipe/Espinacas-con-Garbanzos-Spinach-with-Garbanzo-Beans/Detail.aspx?evt19=1&referringHubId=84","type":"healthy"},{"rating":90,"name":"Granola Bars III","link":"/Recipe/Granola-Bars-III/Detail.aspx?evt19=1&referringHubId=84","type":"healthy"},{"rating":90,"name":"Navy Bean Soup I","link":"/Recipe/Navy-Bean-Soup-I/Detail.aspx?evt19=1&referringHubId=84","type":"healthy"},{"rating":90,"name":"Mango Salsa","link":"/Recipe/Mango-Salsa/Detail.aspx?evt19=1&referringHubId=84","type":"healthy"},{"rating":80,"name":"Slow Cooker Chicken Marrakesh","link":"/Recipe/Slow-Cooker-Chicken-Marrakesh/Detail.aspx?evt19=1&referringHubId=84","type":"healthy"},{"rating":90,"name":"Healthy Garden Salad","link":"/Recipe/Healthy-Garden-Salad/Detail.aspx?evt19=1&referringHubId=84","type":"healthy"},{"rating":100,"name":"Healthier Broiled Tilapia Parmesan","link":"/Recipe/Healthier-Broiled-Tilapia-Parmesan/Detail.aspx?evt19=1&referringHubId=84","type":"healthy"},{"rating":90,"name":"Spiced Slow Cooker Applesauce","link":"/Recipe/Spiced-Slow-Cooker-Applesauce/Detail.aspx?evt19=1&referringHubId=84","type":"healthy"},{"rating":80,"name":"Oat Applesauce Muffins","link":"/Recipe/Oat-Applesauce-Muffins/Detail.aspx?evt19=1&referringHubId=84","type":"healthy"},{"rating":80,"name":"Slow Cooker Chicken Creole","link":"/Recipe/Slow-Cooker-Chicken-Creole/Detail.aspx?evt19=1&referringHubId=84","type":"healthy"},{"rating":80,"name":"Cola Chops","link":"/Recipe/Cola-Chops/Detail.aspx?evt19=1&referringHubId=84","type":"healthy"},{"rating":90,"name":"Fruit Salad in Seconds","link":"/Recipe/Fruit-Salad-in-Seconds/Detail.aspx?evt19=1&referringHubId=84","type":"healthy"},{"rating":90,"name":"Honey Wheat Bread II","link":"/Recipe/Honey-Wheat-Bread-II/Detail.aspx?evt19=1&referringHubId=84","type":"healthy"},{"rating":80,"name":"Alfredo Light","link":"/Recipe/Alfredo-Light/Detail.aspx?evt19=1&referringHubId=84","type":"healthy"},{"rating":80,"name":"Aunt Jewel's Chicken Dressing Casserole","link":"/Recipe/Aunt-Jewels-Chicken-Dressing-Casserole/Detail.aspx?evt19=1&referringHubId=84","type":"healthy"},{"rating":90,"name":"Easy Hummus","link":"/Recipe/Easy-Hummus/Detail.aspx?evt19=1&referringHubId=84","type":"healthy"},{"rating":90,"name":"Pasta with Scallops, Zucchini, and Tomatoes","link":"/Recipe/Pasta-with-Scallops-Zucchini-and-Tomatoes/Detail.aspx?evt19=1&referringHubId=84","type":"healthy"},{"rating":90,"name":"Fresh Strawberry Pie I","link":"/Recipe/Fresh-Strawberry-Pie-I/Detail.aspx?evt19=1&referringHubId=84","type":"healthy"},{"rating":80,"name":"Oatmeal Whole Wheat Quick Bread","link":"/Recipe/Oatmeal-Whole-Wheat-Quick-Bread/Detail.aspx?evt19=1&referringHubId=84","type":"healthy"},{"rating":90,"name":"Wonton Soup","link":"/Recipe/Wonton-Soup/Detail.aspx?evt19=1&referringHubId=84","type":"healthy"},{"rating":90,"name":"Devil's Steak Sauce","link":"/Recipe/Devils-Steak-Sauce/Detail.aspx?evt19=1&referringHubId=84","type":"healthy"},{"rating":90,"name":"Beef or Chicken Marinade","link":"/Recipe/Beef-or-Chicken-Marinade/Detail.aspx?evt19=1&referringHubId=84","type":"healthy"},{"rating":80,"name":"Butternut Squash Fries","link":"/Recipe/Butternut-Squash-Fries/Detail.aspx?evt19=1&referringHubId=84","type":"healthy"},{"rating":90,"name":"Sweet Potato Casserole II","link":"/Recipe/Sweet-Potato-Casserole-II-2/Detail.aspx?evt19=1&referringHubId=84","type":"healthy"},{"rating":90,"name":"Broccoli Soup","link":"/Recipe/Broccoli-Soup/Detail.aspx?evt19=1&referringHubId=84","type":"healthy"},{"rating":90,"name":"Oven Fries","link":"/Recipe/Oven-Fries/Detail.aspx?evt19=1&referringHubId=84","type":"healthy"},{"rating":90,"name":"A Very Popular BBQ Sauce","link":"/Recipe/A-Very-Popular-BBQ-Sauce/Detail.aspx?evt19=1&referringHubId=84","type":"healthy"},{"rating":90,"name":"Fabulous Fajitas","link":"/Recipe/Fabulous-Fajitas/Detail.aspx?evt19=1&referringHubId=84","type":"healthy"},{"rating":90,"name":"Mexican Chicken I","link":"/Recipe/Mexican-Chicken-I/Detail.aspx?evt19=1&referringHubId=84","type":"healthy"},{"rating":90,"name":"Delicious Apple Sauce","link":"/Recipe/Delicious-Apple-Sauce/Detail.aspx?evt19=1&referringHubId=84","type":"healthy"},{"rating":90,"name":"Roasted Asparagus and Mushrooms","link":"/Recipe/Roasted-Asparagus-and-Mushrooms/Detail.aspx?evt19=1&referringHubId=84","type":"healthy"},{"rating":80,"name":"Spicy Black Bean Cakes","link":"/Recipe/Spicy-Black-Bean-Cakes/Detail.aspx?evt19=1&referringHubId=84","type":"healthy"},{"rating":90,"name":"Vegetarian Kale Soup","link":"/Recipe/Vegetarian-Kale-Soup/Detail.aspx?evt19=1&referringHubId=84","type":"healthy"},{"rating":90,"name":"Swiss Chard with Garbanzo Beans and Fresh Tomatoes","link":"/Recipe/Swiss-Chard-with-Garbanzo-Beans-and-Fresh-Tomatoes/Detail.aspx?evt19=1&referringHubId=84","type":"healthy"},{"rating":90,"name":"Veggie Vegetarian Chili","link":"/Recipe/Veggie-Vegetarian-Chili/Detail.aspx?evt19=1&referringHubId=84","type":"healthy"},{"rating":80,"name":"Asparagus, Chicken and Penne Pasta","link":"/Recipe/Asparagus-Chicken-and-Penne-Pasta/Detail.aspx?evt19=1&referringHubId=84","type":"healthy"},{"rating":90,"name":"Apricot Lentil Soup","link":"/Recipe/Apricot-Lentil-Soup/Detail.aspx?evt19=1&referringHubId=84","type":"healthy"},{"rating":90,"name":"Buttermilk Honey Wheat Bread","link":"/Recipe/Buttermilk-Honey-Wheat-Bread/Detail.aspx?evt19=1&referringHubId=84","type":"healthy"},{"rating":90,"name":"Grilled Peanut Butter and Banana Sandwich","link":"/Recipe/Grilled-Peanut-Butter-and-Banana-Sandwich/Detail.aspx?evt19=1&referringHubId=84","type":"healthy"},{"rating":90,"name":"Chocolate Sauce","link":"/Recipe/Chocolate-Sauce/Detail.aspx?evt19=1&referringHubId=84","type":"healthy"},{"rating":100,"name":"Bob's Habanero Hot Sauce - Liquid Fire","link":"/Recipe/Bobs-Habanero-Hot-Sauce---Liquid-Fire/Detail.aspx?evt19=1&referringHubId=84","type":"healthy"},{"rating":80,"name":"Pasta with Asparagus","link":"/Recipe/Pasta-with-Asparagus/Detail.aspx?evt19=1&referringHubId=84","type":"healthy"},{"rating":90,"name":"Baked Potato","link":"/Recipe/Baked-Potato/Detail.aspx?evt19=1&referringHubId=84","type":"healthy"},{"rating":90,"name":"Herbed Chicken Nuggets","link":"/Recipe/Herbed-Chicken-Nuggets/Detail.aspx?evt19=1&referringHubId=84","type":"healthy"},{"rating":90,"name":"Raspberry Sauce","link":"/Recipe/Raspberry-Sauce-4/Detail.aspx?evt19=1&referringHubId=84","type":"healthy"},{"rating":100,"name":"Texas Caviar I","link":"/Recipe/Texas-Caviar-I/Detail.aspx?evt19=1&referringHubId=84","type":"healthy"},{"rating":90,"name":"Salsa II","link":"/Recipe/Salsa-II/Detail.aspx?evt19=1&referringHubId=84","type":"healthy"},{"rating":90,"name":"Butternut Squash Pizzas with Rosemary","link":"/Recipe/Butternut-Squash-Pizzas-with-Rosemary/Detail.aspx?evt19=1&referringHubId=84","type":"healthy"},{"rating":90,"name":"Butternut Squash and Turkey Chili","link":"/Recipe/Butternut-Squash-and-Turkey-Chili/Detail.aspx?evt19=1&referringHubId=84","type":"healthy"},{"rating":90,"name":"Kale Chips","link":"/Recipe/Kale-Chips/Detail.aspx?evt19=1&referringHubId=84","type":"healthy"},{"rating":90,"name":"Lentil Soup III","link":"/Recipe/Lentil-Soup-III/Detail.aspx?evt19=1&referringHubId=84","type":"healthy"},{"rating":90,"name":"Mexican Pasta","link":"/Recipe/Mexican-Pasta/Detail.aspx?evt19=1&referringHubId=84","type":"healthy"},{"rating":90,"name":"Hugh's Dry Rub","link":"/Recipe/Hughs-Dry-Rub/Detail.aspx?evt19=1&referringHubId=84","type":"healthy"},{"rating":90,"name":"Thai Spiced Barbecue Shrimp","link":"/Recipe/Thai-Spiced-Barbecue-Shrimp/Detail.aspx?evt19=1&referringHubId=84","type":"healthy"},{"rating":90,"name":"Pesto Polenta Lasagna","link":"/Recipe/Pesto-Polenta-Lasagna/Detail.aspx?evt19=1&referringHubId=84","type":"healthy"},{"rating":80,"name":"Mushroom Lentil Barley Stew","link":"/Recipe/Mushroom-Lentil-Barley-Stew/Detail.aspx?evt19=1&referringHubId=84","type":"healthy"}]